build_sqli_url.py
build_sqli_url-0.1.0.dist-info/entry_points.txt
build_sqli_url-0.1.0.dist-info/WHEEL
build_sqli_url-0.1.0.dist-info/METADATA
build_sqli_url-0.1.0.dist-info/RECORD
